sallu_bhai/__init__.py
sallu_bhai/cli_tool.py
sallu_bhai/core.py
sallu_bhai-0.1.3.dist-info/LICENSE
sallu_bhai-0.1.3.dist-info/METADATA
sallu_bhai-0.1.3.dist-info/WHEEL
sallu_bhai-0.1.3.dist-info/entry_points.txt
sallu_bhai-0.1.3.dist-info/top_level.txt
sallu_bhai-0.1.3.dist-info/RECORD
