Metadata-Version: 2.1
Name: sallu-bhai
Version: 0.1.3
Summary: UNKNOWN
Home-page: UNKNOWN
License: UNKNOWN
Platform: UNKNOWN
License-File: LICENSE
Requires-Dist: ollama (>=0.1.0)
